zeeklog2pandas.py
zeeklog2pandas-1.0.2.dist-info/AUTHORS.rst
zeeklog2pandas-1.0.2.dist-info/LICENSE
zeeklog2pandas-1.0.2.dist-info/METADATA
zeeklog2pandas-1.0.2.dist-info/WHEEL
zeeklog2pandas-1.0.2.dist-info/top_level.txt
zeeklog2pandas-1.0.2.dist-info/RECORD
