Metadata-Version: 2.1
Name: zeeklog2pandas
Version: 1.0.2
Summary: Read Zeeek/Bro log and log.gz (even broken ones) into a Pandas Dataframe.
Home-page: https://github.com/stratosphereips/zeeklog2pandas
Author: Joaquin Bogado
Author-email: joaquinbogado@duck.com
License: MIT license
Keywords: zeeklog2pandas
Classifier: Development Status :: 4 - Beta
Classifier: Intended Audience :: Developers
Classifier: License :: OSI Approved :: MIT License
Classifier: Natural Language :: English
Classifier: Programming Language :: Python :: 3
Classifier: Programming Language :: Python :: 3.6
Classifier: Programming Language :: Python :: 3.7
Classifier: Programming Language :: Python :: 3.8
Requires-Python: >=3.6
License-File: LICENSE
License-File: AUTHORS.rst
